django_auto_rebase/__init__.py
django_auto_rebase/rebase.py
django_auto_rebase-1.0.0.dist-info/entry_points.txt
django_auto_rebase-1.0.0.dist-info/LICENSE
django_auto_rebase-1.0.0.dist-info/WHEEL
django_auto_rebase-1.0.0.dist-info/METADATA
django_auto_rebase-1.0.0.dist-info/RECORD
