Metadata-Version: 2.1
Name: django-auto-rebase
Version: 1.0.0
Summary: 
Home-page: https://github.com/cs-cordero/django-auto-rebase
License: GPL-3.0
Keywords: django,Django,migrations
Author: Christopher Cordero
Author-email: ccordero@protonmail.com
Requires-Python: >=3.6,<4.0
Classifier: License :: OSI Approved :: GNU General Public License v3 (GPLv3)
Classifier: Programming Language :: Python :: 3
Classifier: Programming Language :: Python :: 3.6
Classifier: Programming Language :: Python :: 3.7
Requires-Dist: Django (>=2.2,<3.0)
Project-URL: Documentation, https://github.com/cs-cordero/django-auto-rebase
Project-URL: Repository, https://github.com/cs-cordero/django-auto-rebase
